jupyterlab_latex/__init__.py
jupyterlab_latex/_version.py
jupyterlab_latex/build.py
jupyterlab_latex/config.py
jupyterlab_latex/synctex.py
jupyterlab_latex/util.py
jupyterlab_latex/api/api.yaml
jupyterlab_latex-4.4.0.data/data/etc/jupyter/jupyter_notebook_config.d/jupyterlab_latex.json
jupyterlab_latex-4.4.0.data/data/etc/jupyter/jupyter_server_config.d/jupyterlab_latex.json
jupyterlab_latex-4.4.0.data/data/share/jupyter/labextensions/@jupyterlab/latex/install.json
jupyterlab_latex-4.4.0.data/data/share/jupyter/labextensions/@jupyterlab/latex/package.json
jupyterlab_latex-4.4.0.data/data/share/jupyter/labextensions/@jupyterlab/latex/static/483c4a0396691993a641.gif
jupyterlab_latex-4.4.0.data/data/share/jupyter/labextensions/@jupyterlab/latex/static/630.73c55664376af96cc6e9.js
jupyterlab_latex-4.4.0.data/data/share/jupyter/labextensions/@jupyterlab/latex/static/630.73c55664376af96cc6e9.js.LICENSE.txt
jupyterlab_latex-4.4.0.data/data/share/jupyter/labextensions/@jupyterlab/latex/static/631.8468ad1483e75e001a90.js
jupyterlab_latex-4.4.0.data/data/share/jupyter/labextensions/@jupyterlab/latex/static/703.a0ce6ec033f2535c4ad9.js
jupyterlab_latex-4.4.0.data/data/share/jupyter/labextensions/@jupyterlab/latex/static/743.282728785686fcbfd6f9.js
jupyterlab_latex-4.4.0.data/data/share/jupyter/labextensions/@jupyterlab/latex/static/743.282728785686fcbfd6f9.js.LICENSE.txt
jupyterlab_latex-4.4.0.data/data/share/jupyter/labextensions/@jupyterlab/latex/static/84.40c822dc3e0e2044d2d5.js
jupyterlab_latex-4.4.0.data/data/share/jupyter/labextensions/@jupyterlab/latex/static/920.35fdcd54da9122febb4e.js
jupyterlab_latex-4.4.0.data/data/share/jupyter/labextensions/@jupyterlab/latex/static/920.35fdcd54da9122febb4e.js.LICENSE.txt
jupyterlab_latex-4.4.0.data/data/share/jupyter/labextensions/@jupyterlab/latex/static/970.6c9fcbe33ca8e44e5114.js
jupyterlab_latex-4.4.0.data/data/share/jupyter/labextensions/@jupyterlab/latex/static/973.76fbceb100ec6922a0c6.js
jupyterlab_latex-4.4.0.dist-info/METADATA
jupyterlab_latex-4.4.0.dist-info/WHEEL
jupyterlab_latex-4.4.0.dist-info/licenses/LICENSE
jupyterlab_latex-4.4.0.dist-info/RECORD
