Metadata-Version: 2.4
Name: jupyterlab_latex
Version: 4.4.0
Summary: JupyterLab extension for running LaTeX
Project-URL: Homepage, https://github.com/jupyterlab/jupyterlab-latex
Project-URL: Bug Tracker, https://github.com/jupyterlab/jupyterlab-latex/issues
Project-URL: Repository, https://github.com/jupyterlab/jupyterlab-latex.git
Author-email: Jupyter Development Team <jupyter@googlegroups.com>
License: Copyright (c) 2017, Project Jupyter Contributors
License-File: LICENSE
Keywords: jupyter,jupyterlab,jupyterlab-extension,latex
Classifier: Framework :: Jupyter
Classifier: Framework :: Jupyter :: JupyterLab
Classifier: Framework :: Jupyter :: JupyterLab :: 4
Classifier: Framework :: Jupyter :: JupyterLab :: Extensions
Classifier: Framework :: Jupyter :: JupyterLab :: Extensions :: Prebuilt
Classifier: License :: OSI Approved :: BSD License
Classifier: Programming Language :: Python
Classifier: Programming Language :: Python :: 3
Classifier: Programming Language :: Python :: 3.8
Classifier: Programming Language :: Python :: 3.9
Classifier: Programming Language :: Python :: 3.10
Classifier: Programming Language :: Python :: 3.11
Classifier: Programming Language :: Python :: 3.12
Requires-Python: >=3.8
Requires-Dist: jupyter-server<3,>=2.0.1
